MayankPyLib/__init__.py
MayankPyLib/myFunction.py
MayankPyLib-0.1.0.dist-info/METADATA
MayankPyLib-0.1.0.dist-info/WHEEL
MayankPyLib-0.1.0.dist-info/top_level.txt
MayankPyLib-0.1.0.dist-info/RECORD
