Metadata-Version: 2.1
Name: MayankPyLib
Version: 0.1.0
Summary: My first Python library
Home-page: UNKNOWN
Author: Me
License: ZD
Platform: UNKNOWN
